{
    "0": {
        "赈灾与民生保障": {
            "民生工程": [
                {
                    "originalText": "○1 ○201广东布政使史奕昂奏、粤东塘汛。旧制烟墩、砌以碎石土砖。望楼、用木建造。嗣经原任藩司石柱、令俱改换青砖。日久风雨飘淋。仍易坍损。徒滋糜费。请仍遵旧制。得旨、石柱原不晓事。如汝所议行。",
                    "translation": "【核心信息】主体: , 性质: \n\n这是 Service 层对原文的白话文翻译。\n\n",
                    "articleId": "201-210_1",
                    "timestamp": 1761126177.267782
                },
                {
                    "originalText": "○209河东河道总督张师载奏、杨桥漫口。现随同刘统勋等、驻工催筑。其杨桥以下。南北两岸各漫口。当此黄河将归故道之时。急宜赶筑以资拦截。已饬属分限办理。得旨、杨桥不悉无人。汝竟宜急赴下游两岸。督办各工。仍与刘统勋等、声息相通。以期全善无虞。勉之",
                    "translation": "【核心信息】主体: 河东河道总督, 性质: \n\n这是 Service 层对原文的白话文翻译。\n\n",
                    "articleId": "201-210_9",
                    "timestamp": 1761126334.068633
                }
            ],
            "赈灾": [
                {
                    "originalText": "○210吏部议覆、盛京将军弘晌奏称、请将失察流民私行渡海之奉天、山东、沿海州县。及巡查各员。严行议处。嗣后如有失察流民。私行渡海。别经发觉者。照台湾流寓民人眷属偷渡例。将沿海州县、及巡查文职官。失察一名至十名者、罚俸一年。十名以上、降一级留任。二十名以上、降一级调用。至武职巡哨洋面。均有稽查之责。如有失察。亦照此例。按其偷渡名数。分别议处。其守口武弁。遇有疎纵。即照盘查不实例、降二级调用。从之。",
                    "translation": "【核心信息】主体: 部议, 性质: \n\n这是 Service 层对原文的白话文翻译。\n\n",
                    "articleId": "201-210_10",
                    "timestamp": 1761126401.540288
                }
            ]
        },
        "军事与外交事务": {
            "外交往来": [
                {
                    "originalText": "○203谕军机大臣等、据秀林等奏、阿奇木伯克公品级迈玛第敏、恳请明年来京。叩祝万寿等语。迈玛第敏、诚心恳请。又系噶岱默特之孙。著照所请。与明年年班伯克等、一同起程前来。近日伊斯堪达尔、额尔德锡尔等、俱准来京。其别城伯克闻之。亦必有告请来京者。但伊等来后。又须派人署缺。各处办事。不可无人。著传谕驻劄回疆各城办事大臣。众伯克内、伊祖父有类噶岱默特、鄂对之从前出力。朕曾施恩者。其子孙若恳请来京。即行具奏。其寻常伯克。概行驳回。",
                    "translation": "【核心信息】主体: , 性质: \n\n这是 Service 层对原文的白话文翻译。\n\n",
                    "articleId": "201-210_3",
                    "timestamp": 1761126224.673528
                },
                {
                    "originalText": "○205达赖喇嘛自代噶起程归国。命固山贝子吴达海饯之。",
                    "translation": "【核心信息】主体: , 性质: \n\n这是 Service 层对原文的白话文翻译。\n\n",
                    "articleId": "201-210_5",
                    "timestamp": 1761126261.158685
                }
            ],
            "边防": [
                {
                    "originalText": "○204升任西宁办事大臣贡楚克扎布奏、堵截贼番出力各员。都司邵能等下部议叙。赏通丁罗成印顶带。",
                    "translation": "【核心信息】主体: 部议, 性质: \n\n这是 Service 层对原文的白话文翻译。\n\n",
                    "articleId": "201-210_4",
                    "timestamp": 1761126247.608563
                }
            ]
        },
        "官场与宫廷生活": {
            "信息交流": [
                {
                    "originalText": "○208河南巡抚硕色奏报、劝民种树育蚕情形。得旨、览奏欣悦。诸事应如此留心。尤应以实也。",
                    "translation": "【核心信息】主体: 河南巡抚, 性质: \n\n这是 Service 层对原文的白话文翻译。\n\n",
                    "articleId": "201-210_8",
                    "timestamp": 1761126303.0295901
                },
                {
                    "originalText": "○207镇国将军释迦保缘事革退。以其子忠福照例袭为三等辅国将军。",
                    "translation": "【核心信息】主体: , 性质: \n\n这是 Service 层对原文的白话文翻译。\n\n",
                    "articleId": "201-210_7",
                    "timestamp": 1761126383.293816
                },
                {
                    "originalText": "○206升河标中军副将王应统、为河南河北总兵官。",
                    "translation": "【核心信息】主体: , 性质: \n\n这是 Service 层对原文的白话文翻译。\n\n",
                    "articleId": "201-210_6",
                    "timestamp": 1761126391.893248
                },
                {
                    "originalText": "○208河南巡抚硕色奏报、劝民种树育蚕情形。得旨、览奏欣悦。诸事应如此留心。尤应以实也。",
                    "translation": "【核心信息】主体: 河南巡抚, 性质: \n\n这是 Service 层对原文的白话文翻译。\n\n",
                    "articleId": "201-210_8",
                    "timestamp": 1761136855.107522
                },
                {
                    "originalText": "○208河南巡抚硕色奏报、劝民种树育蚕情形。得旨、览奏欣悦。诸事应如此留心。尤应以实也。",
                    "translation": "【核心信息】主体: 河南巡抚, 性质: \n\n这是 Service 层对原文的白话文翻译。\n\n",
                    "articleId": "201-210_8",
                    "timestamp": 1761137280.391496
                }
            ]
        },
        "社会治安与司法": {
            "流民": [
                {
                    "originalText": "○210吏部议覆、盛京将军弘晌奏称、请将失察流民私行渡海之奉天、山东、沿海州县。及巡查各员。严行议处。嗣后如有失察流民。私行渡海。别经发觉者。照台湾流寓民人眷属偷渡例。将沿海州县、及巡查文职官。失察一名至十名者、罚俸一年。十名以上、降一级留任。二十名以上、降一级调用。至武职巡哨洋面。均有稽查之责。如有失察。亦照此例。按其偷渡名数。分别议处。其守口武弁。遇有疎纵。即照盘查不实例、降二级调用。从之。",
                    "translation": "【核心信息】主体: 部议, 性质: \n\n这是 Service 层对原文的白话文翻译。\n\n",
                    "articleId": "201-210_10",
                    "timestamp": 1761126362.059912
                }
            ]
        }
    },
    "1": {
        "行政失职": {
            "待补充": [
                {
                    "originalText": "○202又谕曰、吴嗣爵题岁报河道钱粮一疏。尚系乾隆三十七年分、动支收存之数。办理太迟。河道钱粮等项例应按年造报。原欲周知一岁河道工程之多寡钜细。以凭核实稽查。即云俟各司道陆续造送。查核需时。则三十七年之案。亦应在三十九年正月出本断无查办不及之理。今乃迟至四十年冬间具题中间几阅三载。实属迟延。吴嗣爵著交部议处。嗣后河工岁报钱粮俱著次年全数查明。于第三年正月间开印后具题。如有逾期该部即查明参奏。",
                    "translation": "【核心信息】主体: 部议, 性质: \n\n这是 Service 层对原文的白话文翻译。\n\n",
                    "articleId": "201-210_2",
                    "timestamp": 1761126202.46067
                }
            ]
        }
    }
}